{
    "os": "Linux-5.4.0-174-generic-x86_64-with-glibc2.35",
    "python": "3.11.9",
    "heartbeatAt": "2024-04-16T16:32:35.404182",
    "startedAt": "2024-04-16T16:32:34.655670",
    "docker": null,
    "cuda": null,
    "args": [
        "--log_with=wandb"
    ],
    "state": "running",
    "program": "/root/berni/ppo_test.py",
    "codePathLocal": "ppo_test.py",
    "codePath": "ppo_test.py",
    "git": {
        "remote": "git@github.com:zakhardavydov/berni.git",
        "commit": "acb884c433d2f0843f604f53693c576778e3c6a9"
    },
    "email": "zakharchk@gmail.com",
    "root": "/root/berni",
    "host": "74a7c7883937",
    "username": "root",
    "executable": "/root/.cache/pypoetry/virtualenvs/berni-3Dajnqdh-py3.11/bin/python",
    "cpu_count": 28,
    "cpu_count_logical": 56,
    "cpu_freq": {
        "current": 1552.539392857143,
        "min": 1200.0,
        "max": 3500.0
    },
    "cpu_freq_per_core": [
        {
            "current": 1200.09,
            "min": 1200.0,
            "max": 3500.0
        },
        {
            "current": 1200.036,
            "min": 1200.0,
            "max": 3500.0
        },
        {
            "current": 1200.07,
            "min": 1200.0,
            "max": 3500.0
        },
        {
            "current": 3199.885,
            "min": 1200.0,
            "max": 3500.0
        },
        {
            "current": 1202.911,
            "min": 1200.0,
            "max": 3500.0
        },
        {
            "current": 1202.615,
            "min": 1200.0,
            "max": 3500.0
        },
        {
            "current": 1202.923,
            "min": 1200.0,
            "max": 3500.0
        },
        {
            "current": 1203.611,
            "min": 1200.0,
            "max": 3500.0
        },
        {
            "current": 1201.536,
            "min": 1200.0,
            "max": 3500.0
        },
        {
            "current": 1201.084,
            "min": 1200.0,
            "max": 3500.0
        },
        {
            "current": 1203.102,
            "min": 1200.0,
            "max": 3500.0
        },
        {
            "current": 1285.1,
            "min": 1200.0,
            "max": 3500.0
        },
        {
            "current": 2194.601,
            "min": 1200.0,
            "max": 3500.0
        },
        {
            "current": 2344.616,
            "min": 1200.0,
            "max": 3500.0
        },
        {
            "current": 1200.88,
            "min": 1200.0,
            "max": 3500.0
        },
        {
            "current": 1201.137,
            "min": 1200.0,
            "max": 3500.0
        },
        {
            "current": 1202.583,
            "min": 1200.0,
            "max": 3500.0
        },
        {
            "current": 3202.584,
            "min": 1200.0,
            "max": 3500.0
        },
        {
            "current": 1724.735,
            "min": 1200.0,
            "max": 3500.0
        },
        {
            "current": 1200.0,
            "min": 1200.0,
            "max": 3500.0
        },
        {
            "current": 1702.209,
            "min": 1200.0,
            "max": 3500.0
        },
        {
            "current": 1803.867,
            "min": 1200.0,
            "max": 3500.0
        },
        {
            "current": 2306.642,
            "min": 1200.0,
            "max": 3500.0
        },
        {
            "current": 1403.121,
            "min": 1200.0,
            "max": 3500.0
        },
        {
            "current": 1356.397,
            "min": 1200.0,
            "max": 3500.0
        },
        {
            "current": 2150.21,
            "min": 1200.0,
            "max": 3500.0
        },
        {
            "current": 1408.065,
            "min": 1200.0,
            "max": 3500.0
        },
        {
            "current": 1201.722,
            "min": 1200.0,
            "max": 3500.0
        },
        {
            "current": 1200.968,
            "min": 1200.0,
            "max": 3500.0
        },
        {
            "current": 1200.041,
            "min": 1200.0,
            "max": 3500.0
        },
        {
            "current": 1202.11,
            "min": 1200.0,
            "max": 3500.0
        },
        {
            "current": 3243.42,
            "min": 1200.0,
            "max": 3500.0
        },
        {
            "current": 1200.521,
            "min": 1200.0,
            "max": 3500.0
        },
        {
            "current": 1200.784,
            "min": 1200.0,
            "max": 3500.0
        },
        {
            "current": 1200.587,
            "min": 1200.0,
            "max": 3500.0
        },
        {
            "current": 1200.224,
            "min": 1200.0,
            "max": 3500.0
        },
        {
            "current": 1199.973,
            "min": 1200.0,
            "max": 3500.0
        },
        {
            "current": 1200.002,
            "min": 1200.0,
            "max": 3500.0
        },
        {
            "current": 1201.193,
            "min": 1200.0,
            "max": 3500.0
        },
        {
            "current": 1258.035,
            "min": 1200.0,
            "max": 3500.0
        },
        {
            "current": 2015.454,
            "min": 1200.0,
            "max": 3500.0
        },
        {
            "current": 2326.269,
            "min": 1200.0,
            "max": 3500.0
        },
        {
            "current": 1201.485,
            "min": 1200.0,
            "max": 3500.0
        },
        {
            "current": 1200.488,
            "min": 1200.0,
            "max": 3500.0
        },
        {
            "current": 1200.662,
            "min": 1200.0,
            "max": 3500.0
        },
        {
            "current": 3291.14,
            "min": 1200.0,
            "max": 3500.0
        },
        {
            "current": 1355.072,
            "min": 1200.0,
            "max": 3500.0
        },
        {
            "current": 1202.257,
            "min": 1200.0,
            "max": 3500.0
        },
        {
            "current": 1700.498,
            "min": 1200.0,
            "max": 3500.0
        },
        {
            "current": 1623.797,
            "min": 1200.0,
            "max": 3500.0
        },
        {
            "current": 2014.197,
            "min": 1200.0,
            "max": 3500.0
        },
        {
            "current": 1390.281,
            "min": 1200.0,
            "max": 3500.0
        },
        {
            "current": 1367.804,
            "min": 1200.0,
            "max": 3500.0
        },
        {
            "current": 2086.106,
            "min": 1200.0,
            "max": 3500.0
        },
        {
            "current": 1636.058,
            "min": 1200.0,
            "max": 3500.0
        },
        {
            "current": 1200.573,
            "min": 1200.0,
            "max": 3500.0
        }
    ],
    "disk": {
        "/": {
            "total": 78.0,
            "used": 47.49303436279297
        }
    },
    "gpu": "Tesla V100-SXM2-16GB",
    "gpu_count": 2,
    "gpu_devices": [
        {
            "name": "Tesla V100-SXM2-16GB",
            "memory_total": 17179869184
        },
        {
            "name": "Tesla V100-SXM2-16GB",
            "memory_total": 17179869184
        }
    ],
    "memory": {
        "total": 251.7745475769043
    }
}
